xdi_validator/XDI_validator.py
xdi_validator/__init__.py
xdi_validator-1.2.0.dist-info/METADATA
xdi_validator-1.2.0.dist-info/WHEEL
xdi_validator-1.2.0.dist-info/licenses/LICENSE
xdi_validator-1.2.0.dist-info/RECORD
