Metadata-Version: 2.4
Name: xdi_validator
Version: 1.2.0
Summary: A standalone JSON Schema based validator for XDI files used to save XAS data aiming to be fully compliant with the XDI/1.0 specification..
Project-URL: Homepage, https://github.com/AAAlvesJr/XDI-Validator
Project-URL: Documentation, https://github.com/AAAlvesJr/XDI-Validator
Project-URL: Repository, https://github.com/AAAlvesJr/XDI-Validator.git
Author-email: Antonio Augusto Alves Jr <aalvesju@gmail.com>
Maintainer-email: Antonio Augusto Alves Jr <aalvesju@gmail.com>
License-Expression: MIT
License-File: LICENSE
Keywords: validation,xas,xdi
Classifier: Development Status :: 4 - Beta
Classifier: Intended Audience :: Developers
Classifier: Intended Audience :: Science/Research
Classifier: License :: OSI Approved :: MIT License
Classifier: Programming Language :: Python
Requires-Python: >=3.13
Requires-Dist: jsonschema>=4.23.0
